[
  {
    "emoji": "😼",
    "ideation": "The wry cat smile is a performance of predator-like confidence and sly amusement. Unlike a human smirk, this should feel feline: eyes that are half-lidded and predatory, occasionally narrowing into 'hunter slits.' The ears are implied by the way the lids angle—sharply outward to suggest alertness. The mouth is the key: it uses an asymmetrical smirk (phase 1.57) that grows in amplitude as the 'cat' savors a clever thought. The color palette moves from a warm, orange tabby gold to a sharper, neon amber to emphasize a mischievous 'gotcha' moment.",
    "frames": [
      [
        {
          "state": "EyeGazeX",
          "parameters": {
            "eye_side": "both",
            "gaze_x": 0.0
          }
        },
        {
          "state": "EyeGazeY",
          "parameters": {
            "eye_side": "both",
            "gaze_y": 0.0
          }
        },
        {
          "state": "EyeScaleX",
          "parameters": {
            "eye_side": "both",
            "scale_x": 0.5
          }
        },
        {
          "state": "EyeScaleY",
          "parameters": {
            "eye_side": "both",
            "scale_y": 0.45
          }
        },
        {
          "state": "EyeLidHeight",
          "parameters": {
            "eye_side": "both",
            "lid_height": 0.15
          }
        },
        {
          "state": "EyeLidAngle",
          "parameters": {
            "eye_side": "both",
            "lid_angle": 12
          }
        },
        {
          "state": "EyeColor",
          "parameters": {
            "eye_side": "both",
            "color": "#D97B24"
          }
        },
        {
          "state": "MouthSine",
          "parameters": {
            "frequency": 0.5,
            "amplitude": 0.1,
            "phase": 1.57,
            "phase_increment": 0.0,
            "color": "#BF651F"
          }
        }
      ],
      [
        {
          "state": "EyeGazeX",
          "parameters": {
            "eye_side": "both",
            "gaze_x": 0.25
          }
        },
        {
          "state": "EyeGazeY",
          "parameters": {
            "eye_side": "both",
            "gaze_y": -0.1
          }
        },
        {
          "state": "EyeScaleX",
          "parameters": {
            "eye_side": "both",
            "scale_x": 0.5
          }
        },
        {
          "state": "EyeScaleY",
          "parameters": {
            "eye_side": "both",
            "scale_y": 0.5
          }
        },
        {
          "state": "EyeLidHeight",
          "parameters": {
            "eye_side": "both",
            "lid_height": 0.15
          }
        },
        {
          "state": "EyeLidAngle",
          "parameters": {
            "eye_side": "both",
            "lid_angle": 12
          }
        },
        {
          "state": "EyeColor",
          "parameters": {
            "eye_side": "both",
            "color": "#F28C33"
          }
        },
        {
          "state": "MouthSine",
          "parameters": {
            "frequency": 0.5,
            "amplitude": 0.25,
            "phase": 1.57,
            "phase_increment": 0.0,
            "color": "#D96E26"
          }
        }
      ],
      [
        {
          "state": "EyeGazeX",
          "parameters": {
            "eye_side": "both",
            "gaze_x": 0.25
          }
        },
        {
          "state": "EyeGazeY",
          "parameters": {
            "eye_side": "both",
            "gaze_y": -0.1
          }
        },
        {
          "state": "EyeScaleX",
          "parameters": {
            "eye_side": "both",
            "scale_x": 0.35
          }
        },
        {
          "state": "EyeScaleY",
          "parameters": {
            "eye_side": "both",
            "scale_y": 0.3
          }
        },
        {
          "state": "EyeLidHeight",
          "parameters": {
            "eye_side": "both",
            "lid_height": -0.2
          }
        },
        {
          "state": "EyeLidAngle",
          "parameters": {
            "eye_side": "both",
            "lid_angle": 25
          }
        },
        {
          "state": "EyeColor",
          "parameters": {
            "eye_side": "both",
            "color": "#FFC14D"
          }
        },
        {
          "state": "MouthSine",
          "parameters": {
            "frequency": 0.5,
            "amplitude": 0.45,
            "phase": 1.8,
            "phase_increment": 0.0,
            "color": "#E65A1E"
          }
        }
      ],
      [
        {
          "state": "EyeGazeX",
          "parameters": {
            "eye_side": "both",
            "gaze_x": 0.25
          }
        },
        {
          "state": "EyeGazeY",
          "parameters": {
            "eye_side": "both",
            "gaze_y": -0.1
          }
        },
        {
          "state": "EyeScaleX",
          "parameters": {
            "eye_side": "both",
            "scale_x": 0.35
          }
        },
        {
          "state": "EyeScaleY",
          "parameters": {
            "eye_side": "both",
            "scale_y": 0.05
          }
        },
        {
          "state": "EyeLidHeight",
          "parameters": {
            "eye_side": "both",
            "lid_height": -0.9
          }
        },
        {
          "state": "EyeLidAngle",
          "parameters": {
            "eye_side": "both",
            "lid_angle": 25
          }
        },
        {
          "state": "EyeColor",
          "parameters": {
            "eye_side": "both",
            "color": "#FFC14D"
          }
        },
        {
          "state": "MouthSine",
          "parameters": {
            "frequency": 0.5,
            "amplitude": 0.45,
            "phase": 1.8,
            "phase_increment": 0.05,
            "color": "#E65A1E"
          }
        }
      ],
      [
        {
          "state": "EyeGazeX",
          "parameters": {
            "eye_side": "both",
            "gaze_x": 0.25
          }
        },
        {
          "state": "EyeGazeY",
          "parameters": {
            "eye_side": "both",
            "gaze_y": -0.1
          }
        },
        {
          "state": "EyeScaleX",
          "parameters": {
            "eye_side": "both",
            "scale_x": 0.55
          }
        },
        {
          "state": "EyeScaleY",
          "parameters": {
            "eye_side": "both",
            "scale_y": 0.6
          }
        },
        {
          "state": "EyeLidHeight",
          "parameters": {
            "eye_side": "both",
            "lid_height": 0.4
          }
        },
        {
          "state": "EyeLidAngle",
          "parameters": {
            "eye_side": "both",
            "lid_angle": 30
          }
        },
        {
          "state": "EyeColor",
          "parameters": {
            "eye_side": "both",
            "color": "#FFD35A"
          }
        },
        {
          "state": "MouthSine",
          "parameters": {
            "frequency": 0.8,
            "amplitude": 0.55,
            "phase": 1.57,
            "phase_increment": 0.0,
            "color": "#FF4500"
          }
        }
      ],
      [
        {
          "state": "EyeGazeX",
          "parameters": {
            "eye_side": "both",
            "gaze_x": 0.1
          }
        },
        {
          "state": "EyeGazeY",
          "parameters": {
            "eye_side": "both",
            "gaze_y": 0.0
          }
        },
        {
          "state": "EyeScaleX",
          "parameters": {
            "eye_side": "both",
            "scale_x": 0.5
          }
        },
        {
          "state": "EyeScaleY",
          "parameters": {
            "eye_side": "both",
            "scale_y": 0.4
          }
        },
        {
          "state": "EyeLidHeight",
          "parameters": {
            "eye_side": "both",
            "lid_height": 0.1
          }
        },
        {
          "state": "EyeLidAngle",
          "parameters": {
            "eye_side": "both",
            "lid_angle": 15
          }
        },
        {
          "state": "EyeColor",
          "parameters": {
            "eye_side": "both",
            "color": "#D97B24"
          }
        },
        {
          "state": "MouthSine",
          "parameters": {
            "frequency": 0.3,
            "amplitude": 0.2,
            "phase": 1.57,
            "phase_increment": 0.0,
            "color": "#BF651F"
          }
        }
      ]
    ]
  }
]
