[
  {
    "emoji": "💲",
    "ideation": "The heavy dollar sign is personified as a system calculating market value, hitting a jackpot, and then settling into a state of high-value luxury. The eyes act as 'digit reels,' initially spinning with data before locking into high-contrast 'mint-green' dollar icons. The mouth represents the currency flow: starting as a flat, professional financial line, it transforms into a rhythmic, rolling 'ticker tape' wave as the profit accumulates. The color palette shifts from a reserved bank-vault grey to a vibrant, glowing treasury green, concluding with a shimmering gold that suggests peak asset appreciation.",
    "frames": [
      [
        {
          "state": "EyeGazeX",
          "parameters": {
            "eye_side": "both",
            "gaze_x": 0.0
          }
        },
        {
          "state": "EyeGazeY",
          "parameters": {
            "eye_side": "both",
            "gaze_y": 0.0
          }
        },
        {
          "state": "EyeScaleX",
          "parameters": {
            "eye_side": "both",
            "scale_x": 0.45
          }
        },
        {
          "state": "EyeScaleY",
          "parameters": {
            "eye_side": "both",
            "scale_y": 0.45
          }
        },
        {
          "state": "EyeLidHeight",
          "parameters": {
            "eye_side": "both",
            "lid_height": 0.15
          }
        },
        {
          "state": "EyeLidAngle",
          "parameters": {
            "eye_side": "both",
            "lid_angle": 0
          }
        },
        {
          "state": "EyeColor",
          "parameters": {
            "eye_side": "both",
            "color": "#889988"
          }
        },
        {
          "state": "MouthSine",
          "parameters": {
            "frequency": 0.1,
            "amplitude": 0.02,
            "phase": 0.0,
            "phase_increment": 0.0,
            "color": "#667766"
          }
        }
      ],
      [
        {
          "state": "EyeGazeX",
          "parameters": {
            "eye_side": "both",
            "gaze_x": -0.6
          }
        },
        {
          "state": "EyeGazeY",
          "parameters": {
            "eye_side": "both",
            "gaze_y": 0.2
          }
        },
        {
          "state": "EyeScaleX",
          "parameters": {
            "eye_side": "both",
            "scale_x": 0.45
          }
        },
        {
          "state": "EyeScaleY",
          "parameters": {
            "eye_side": "both",
            "scale_y": 0.45
          }
        },
        {
          "state": "EyeLidHeight",
          "parameters": {
            "eye_side": "both",
            "lid_height": 0.15
          }
        },
        {
          "state": "EyeLidAngle",
          "parameters": {
            "eye_side": "both",
            "lid_angle": 0
          }
        },
        {
          "state": "EyeColor",
          "parameters": {
            "eye_side": "both",
            "color": "#99AA99"
          }
        },
        {
          "state": "MouthSine",
          "parameters": {
            "frequency": 1.5,
            "amplitude": 0.08,
            "phase": 0.0,
            "phase_increment": 0.1,
            "color": "#667766"
          }
        }
      ],
      [
        {
          "state": "EyeGazeX",
          "parameters": {
            "eye_side": "both",
            "gaze_x": 0.0
          }
        },
        {
          "state": "EyeGazeY",
          "parameters": {
            "eye_side": "both",
            "gaze_y": 0.2
          }
        },
        {
          "state": "EyeScaleX",
          "parameters": {
            "eye_side": "both",
            "scale_x": 0.55
          }
        },
        {
          "state": "EyeScaleY",
          "parameters": {
            "eye_side": "both",
            "scale_y": 0.65
          }
        },
        {
          "state": "EyeLidHeight",
          "parameters": {
            "eye_side": "both",
            "lid_height": 0.6
          }
        },
        {
          "state": "EyeLidAngle",
          "parameters": {
            "eye_side": "both",
            "lid_angle": 8
          }
        },
        {
          "state": "EyeColor",
          "parameters": {
            "eye_side": "both",
            "color": "#2ECC71"
          }
        },
        {
          "state": "MouthSine",
          "parameters": {
            "frequency": 0.8,
            "amplitude": 0.35,
            "phase": -0.5,
            "phase_increment": 0.25,
            "color": "#27AE60"
          }
        }
      ],
      [
        {
          "state": "EyeGazeX",
          "parameters": {
            "eye_side": "both",
            "gaze_x": 0.0
          }
        },
        {
          "state": "EyeGazeY",
          "parameters": {
            "eye_side": "both",
            "gaze_y": 0.2
          }
        },
        {
          "state": "EyeScaleX",
          "parameters": {
            "eye_side": "both",
            "scale_x": 0.55
          }
        },
        {
          "state": "EyeScaleY",
          "parameters": {
            "eye_side": "both",
            "scale_y": 0.85
          }
        },
        {
          "state": "EyeLidHeight",
          "parameters": {
            "eye_side": "both",
            "lid_height": 0.9
          }
        },
        {
          "state": "EyeLidAngle",
          "parameters": {
            "eye_side": "both",
            "lid_angle": 15
          }
        },
        {
          "state": "EyeColor",
          "parameters": {
            "eye_side": "both",
            "color": "#00FF66"
          }
        },
        {
          "state": "MouthSine",
          "parameters": {
            "frequency": 3.0,
            "amplitude": 0.7,
            "phase": -0.5,
            "phase_increment": 0.8,
            "color": "#00CC44"
          }
        }
      ],
      [
        {
          "state": "EyeGazeX",
          "parameters": {
            "eye_side": "both",
            "gaze_x": 0.0
          }
        },
        {
          "state": "EyeGazeY",
          "parameters": {
            "eye_side": "both",
            "gaze_y": 0.2
          }
        },
        {
          "state": "EyeScaleX",
          "parameters": {
            "eye_side": "both",
            "scale_x": 0.75
          }
        },
        {
          "state": "EyeScaleY",
          "parameters": {
            "eye_side": "both",
            "scale_y": 0.4
          }
        },
        {
          "state": "EyeLidHeight",
          "parameters": {
            "eye_side": "both",
            "lid_height": 0.25
          }
        },
        {
          "state": "EyeLidAngle",
          "parameters": {
            "eye_side": "both",
            "lid_angle": -10
          }
        },
        {
          "state": "EyeColor",
          "parameters": {
            "eye_side": "both",
            "color": "#F1C40F"
          }
        },
        {
          "state": "MouthSine",
          "parameters": {
            "frequency": 10.0,
            "amplitude": 0.85,
            "phase": -0.5,
            "phase_increment": 1.2,
            "color": "#F39C12"
          }
        }
      ],
      [
        {
          "state": "EyeGazeX",
          "parameters": {
            "eye_side": "both",
            "gaze_x": 0.2
          }
        },
        {
          "state": "EyeGazeY",
          "parameters": {
            "eye_side": "both",
            "gaze_y": 0.1
          }
        },
        {
          "state": "EyeScaleX",
          "parameters": {
            "eye_side": "both",
            "scale_x": 0.5
          }
        },
        {
          "state": "EyeScaleY",
          "parameters": {
            "eye_side": "both",
            "scale_y": 0.5
          }
        },
        {
          "state": "EyeLidHeight",
          "parameters": {
            "eye_side": "both",
            "lid_height": 0.4
          }
        },
        {
          "state": "EyeLidAngle",
          "parameters": {
            "eye_side": "both",
            "lid_angle": 5
          }
        },
        {
          "state": "EyeColor",
          "parameters": {
            "eye_side": "both",
            "color": "#FFD700"
          }
        },
        {
          "state": "MouthSine",
          "parameters": {
            "frequency": 0.5,
            "amplitude": 0.25,
            "phase": 0.0,
            "phase_increment": 0.05,
            "color": "#DAA520"
          }
        }
      ]
    ]
  }
]
