[
  {
    "emoji": "🥽",
    "ideation": "The goggles animation personifies the act of specialized observation—be it chemistry, swimming, or welding. The sequence begins with a focused preparation, pulling the 'straps' tight (narrowing the eyes and lids). The eyes then become twin portals of intense inspection, scanning the environment through a protective lens. The mouth acts as the mechanical seal or the focused breathing of the wearer, starting tight and moving into a bubbling, pressurized wave. The climax is a high-contrast 'discovery' moment where the eyes flare with bright cyan light as if reflecting an experiment or a clear underwater view, followed by a cool, technical settling into sustained operation.",
    "frames": [
      [
        {
          "state": "EyeGazeX",
          "parameters": {
            "eye_side": "both",
            "gaze_x": 0.0
          }
        },
        {
          "state": "EyeGazeY",
          "parameters": {
            "eye_side": "both",
            "gaze_y": 0.0
          }
        },
        {
          "state": "EyeScaleX",
          "parameters": {
            "eye_side": "both",
            "scale_x": 0.4
          }
        },
        {
          "state": "EyeScaleY",
          "parameters": {
            "eye_side": "both",
            "scale_y": 0.4
          }
        },
        {
          "state": "EyeLidHeight",
          "parameters": {
            "eye_side": "both",
            "lid_height": -0.1
          }
        },
        {
          "state": "EyeLidAngle",
          "parameters": {
            "eye_side": "both",
            "lid_angle": -5
          }
        },
        {
          "state": "EyeColor",
          "parameters": {
            "eye_side": "both",
            "color": "#40E0D0"
          }
        },
        {
          "state": "MouthSine",
          "parameters": {
            "frequency": 4.0,
            "amplitude": 0.1,
            "phase": 0.0,
            "phase_increment": 0.0,
            "color": "#20B2AA"
          }
        }
      ],
      [
        {
          "state": "EyeGazeX",
          "parameters": {
            "eye_side": "both",
            "gaze_x": 0.0
          }
        },
        {
          "state": "EyeGazeY",
          "parameters": {
            "eye_side": "both",
            "gaze_y": 0.0
          }
        },
        {
          "state": "EyeScaleX",
          "parameters": {
            "eye_side": "both",
            "scale_x": 0.35
          }
        },
        {
          "state": "EyeScaleY",
          "parameters": {
            "eye_side": "both",
            "scale_y": 0.35
          }
        },
        {
          "state": "EyeLidHeight",
          "parameters": {
            "eye_side": "both",
            "lid_height": -0.2
          }
        },
        {
          "state": "EyeLidAngle",
          "parameters": {
            "eye_side": "both",
            "lid_angle": -5
          }
        },
        {
          "state": "EyeColor",
          "parameters": {
            "eye_side": "both",
            "color": "#00CED1"
          }
        },
        {
          "state": "MouthSine",
          "parameters": {
            "frequency": 6.5,
            "amplitude": 0.25,
            "phase": 0.0,
            "phase_increment": 0.12,
            "color": "#008B8B"
          }
        }
      ],
      [
        {
          "state": "EyeGazeX",
          "parameters": {
            "eye_side": "both",
            "gaze_x": -0.6
          }
        },
        {
          "state": "EyeGazeY",
          "parameters": {
            "eye_side": "both",
            "gaze_y": 0.3
          }
        },
        {
          "state": "EyeScaleX",
          "parameters": {
            "eye_side": "both",
            "scale_x": 0.35
          }
        },
        {
          "state": "EyeScaleY",
          "parameters": {
            "eye_side": "both",
            "scale_y": 0.45
          }
        },
        {
          "state": "EyeLidHeight",
          "parameters": {
            "eye_side": "both",
            "lid_height": 0.2
          }
        },
        {
          "state": "EyeLidAngle",
          "parameters": {
            "eye_side": "both",
            "lid_angle": -5
          }
        },
        {
          "state": "EyeColor",
          "parameters": {
            "eye_side": "both",
            "color": "#00CED1"
          }
        },
        {
          "state": "MouthSine",
          "parameters": {
            "frequency": 1.2,
            "amplitude": 0.15,
            "phase": 0.0,
            "phase_increment": 0.05,
            "color": "#008B8B"
          }
        }
      ],
      [
        {
          "state": "EyeGazeX",
          "parameters": {
            "eye_side": "both",
            "gaze_x": 0.75
          }
        },
        {
          "state": "EyeGazeY",
          "parameters": {
            "eye_side": "both",
            "gaze_y": -0.2
          }
        },
        {
          "state": "EyeScaleX",
          "parameters": {
            "eye_side": "both",
            "scale_x": 0.35
          }
        },
        {
          "state": "EyeScaleY",
          "parameters": {
            "eye_side": "both",
            "scale_y": 0.45
          }
        },
        {
          "state": "EyeLidHeight",
          "parameters": {
            "eye_side": "both",
            "lid_height": 0.2
          }
        },
        {
          "state": "EyeLidAngle",
          "parameters": {
            "eye_side": "both",
            "lid_angle": -5
          }
        },
        {
          "state": "EyeColor",
          "parameters": {
            "eye_side": "both",
            "color": "#00CED1"
          }
        },
        {
          "state": "MouthSine",
          "parameters": {
            "frequency": 1.2,
            "amplitude": 0.15,
            "phase": 0.0,
            "phase_increment": 0.05,
            "color": "#008B8B"
          }
        }
      ],
      [
        {
          "state": "EyeGazeX",
          "parameters": {
            "eye_side": "both",
            "gaze_x": 0.0
          }
        },
        {
          "state": "EyeGazeY",
          "parameters": {
            "eye_side": "both",
            "gaze_y": 0.0
          }
        },
        {
          "state": "EyeScaleX",
          "parameters": {
            "eye_side": "both",
            "scale_x": 0.7
          }
        },
        {
          "state": "EyeScaleY",
          "parameters": {
            "eye_side": "both",
            "scale_y": 0.7
          }
        },
        {
          "state": "EyeLidHeight",
          "parameters": {
            "eye_side": "both",
            "lid_height": 0.6
          }
        },
        {
          "state": "EyeLidAngle",
          "parameters": {
            "eye_side": "both",
            "lid_angle": 12
          }
        },
        {
          "state": "EyeColor",
          "parameters": {
            "eye_side": "both",
            "color": "#E0FFFF"
          }
        },
        {
          "state": "MouthSine",
          "parameters": {
            "frequency": 0.5,
            "amplitude": 0.4,
            "phase": 1.57,
            "phase_increment": 0.3,
            "color": "#7FFFD4"
          }
        }
      ],
      [
        {
          "state": "EyeGazeX",
          "parameters": {
            "eye_side": "both",
            "gaze_x": 0.0
          }
        },
        {
          "state": "EyeGazeY",
          "parameters": {
            "eye_side": "both",
            "gaze_y": 0.0
          }
        },
        {
          "state": "EyeScaleX",
          "parameters": {
            "eye_side": "both",
            "scale_x": 0.6
          }
        },
        {
          "state": "EyeScaleY",
          "parameters": {
            "eye_side": "both",
            "scale_y": 0.6
          }
        },
        {
          "state": "EyeLidHeight",
          "parameters": {
            "eye_side": "both",
            "lid_height": 0.4
          }
        },
        {
          "state": "EyeLidAngle",
          "parameters": {
            "eye_side": "both",
            "lid_angle": 12
          }
        },
        {
          "state": "EyeColor",
          "parameters": {
            "eye_side": "both",
            "color": "#40E0D0"
          }
        },
        {
          "state": "MouthSine",
          "parameters": {
            "frequency": 3.5,
            "amplitude": 0.6,
            "phase": 1.57,
            "phase_increment": 0.6,
            "color": "#E0FFFF"
          }
        }
      ],
      [
        {
          "state": "EyeGazeX",
          "parameters": {
            "eye_side": "both",
            "gaze_x": 0.0
          }
        },
        {
          "state": "EyeGazeY",
          "parameters": {
            "eye_side": "both",
            "gaze_y": 0.0
          }
        },
        {
          "state": "EyeScaleX",
          "parameters": {
            "eye_side": "both",
            "scale_x": 0.5
          }
        },
        {
          "state": "EyeScaleY",
          "parameters": {
            "eye_side": "both",
            "scale_y": 0.5
          }
        },
        {
          "state": "EyeLidHeight",
          "parameters": {
            "eye_side": "both",
            "lid_height": 0.2
          }
        },
        {
          "state": "EyeLidAngle",
          "parameters": {
            "eye_side": "both",
            "lid_angle": 0
          }
        },
        {
          "state": "EyeColor",
          "parameters": {
            "eye_side": "both",
            "color": "#00CED1"
          }
        },
        {
          "state": "MouthSine",
          "parameters": {
            "frequency": 0.8,
            "amplitude": 0.05,
            "phase": 1.57,
            "phase_increment": 0.02,
            "color": "#008B8B"
          }
        }
      ]
    ]
  }
]
